sage/tools/__init__.py
sage/tools/_version.py
sage/tools/agent_training/__init__.py
sage/tools/agent_training/config.py
sage/tools/agent_training/data_formatter.py
sage/tools/agent_training/dialog_processor.py
sage/tools/agent_training/evaluator.py
sage/tools/agent_training/reward_model.py
sage/tools/agent_training/sft_trainer.py
sage/tools/cli/__init__.py
sage/tools/cli/commands/__init__.py
sage/tools/cli/commands/dev/__init__.py
sage/tools/cli/commands/dev/data.py
sage/tools/cli/commands/dev/docs.py
sage/tools/cli/commands/dev/examples.py
sage/tools/cli/commands/dev/main.py
sage/tools/cli/commands/dev/maintenance.py
sage/tools/cli/commands/dev/models.py
sage/tools/cli/commands/dev/package_version.py
sage/tools/cli/commands/dev/maintain/__init__.py
sage/tools/cli/commands/dev/package/__init__.py
sage/tools/cli/commands/dev/project/__init__.py
sage/tools/cli/commands/dev/quality/__init__.py
sage/tools/cli/commands/dev/resource/__init__.py
sage/tools/cli/utils/dev_check.py
sage/tools/cli/utils/llm_detection.py
sage/tools/dev/__init__.py
sage/tools/dev/cli.py
sage/tools/dev/core/__init__.py
sage/tools/dev/core/bytecode_compiler.py
sage/tools/dev/core/compilation.py
sage/tools/dev/core/config.py
sage/tools/dev/core/exceptions.py
sage/tools/dev/core/toolkit.py
sage/tools/dev/examples/analyzer.py
sage/tools/dev/examples/models.py
sage/tools/dev/examples/runner.py
sage/tools/dev/examples/strategies.py
sage/tools/dev/examples/suite.py
sage/tools/dev/examples/utils.py
sage/tools/dev/hooks/__init__.py
sage/tools/dev/hooks/installer.py
sage/tools/dev/hooks/manager.py
sage/tools/dev/hooks/templates/pre-commit
sage/tools/dev/maintenance/__init__.py
sage/tools/dev/maintenance/devnotes_organizer.py
sage/tools/dev/maintenance/metadata_fixer.py
sage/tools/dev/maintenance/ruff_updater.py
sage/tools/dev/models/__init__.py
sage/tools/dev/models/cache.py
sage/tools/dev/tools/__init__.py
sage/tools/dev/tools/architecture_checker.py
sage/tools/dev/tools/build_artifacts_manager.py
isage_tools-0.2.3.2.dist-info/METADATA
isage_tools-0.2.3.2.dist-info/WHEEL
isage_tools-0.2.3.2.dist-info/entry_points.txt
isage_tools-0.2.3.2.dist-info/top_level.txt
isage_tools-0.2.3.2.dist-info/RECORD
