Metadata-Version: 2.4
Name: isage-tools
Version: 0.2.3.2
Summary: SAGE Development Tools - CLI, Web UI, and Development Utilities
Author-email: IntelliStream Team <shuhao_zhang@hust.edu.cn>
License: MIT
Project-URL: Homepage, https://github.com/intellistream/SAGE
Project-URL: Documentation, https://intellistream.github.io/SAGE-Pub/
Project-URL: Repository, https://github.com/intellistream/SAGE.git
Project-URL: Bug Tracker, https://github.com/intellistream/SAGE/issues
Keywords: sage,tools,cli,development,devtools,intellistream
Classifier: Development Status :: 4 - Beta
Classifier: Intended Audience :: Developers
Classifier: Intended Audience :: System Administrators
Classifier: Programming Language :: Python :: 3
Classifier: Programming Language :: Python :: 3.11
Classifier: Programming Language :: Python :: 3.12
Classifier: Topic :: Software Development :: Libraries :: Python Modules
Classifier: Topic :: Scientific/Engineering :: Artificial Intelligence
Classifier: Topic :: Utilities
Requires-Python: >=3.11
Requires-Dist: typer<1.0.0,>=0.15.0
Requires-Dist: rich<14.0.0,>=13.0.0
Requires-Dist: click<9.0.0,>=8.0.0
Requires-Dist: jinja2<4.0.0,>=3.1.0
Requires-Dist: markdown<4.0.0,>=3.4.4
Requires-Dist: markupsafe>=2.0.1
Requires-Dist: packaging>=24.2
Requires-Dist: huggingface-hub<1.0.0,>=0.34.0
Requires-Dist: filelock<4.0.0,>=3.16.0
Requires-Dist: urllib3<2.4.0,>=1.24.2
Provides-Extra: dev
Requires-Dist: pytest>=7.4.0; extra == "dev"
Requires-Dist: pytest-cov>=4.0.0; extra == "dev"
Requires-Dist: pytest-asyncio>=0.21.0; extra == "dev"
Requires-Dist: pytest-mock>=3.10.0; extra == "dev"
Requires-Dist: pytest-timeout>=2.1.0; extra == "dev"
Requires-Dist: pytest-benchmark>=4.0.0; extra == "dev"
Requires-Dist: ruff==0.14.6; extra == "dev"
Requires-Dist: mypy>=1.7.0; extra == "dev"
Requires-Dist: black>=23.0.0; extra == "dev"
Requires-Dist: isort>=5.10.0; extra == "dev"
Requires-Dist: flake8>=5.0.0; extra == "dev"
Requires-Dist: bandit>=1.7.0; extra == "dev"
Requires-Dist: safety>=2.3.0; extra == "dev"
Requires-Dist: coverage>=7.0.0; extra == "dev"
Requires-Dist: virtualenv>=20.31.2; extra == "dev"
Provides-Extra: all
Requires-Dist: isage-tools[dev]; extra == "all"
